clesperanto/__init__.py
clesperanto/__main__.py
clesperanto/_clesperanto.py
clesperanto-0.1.3.dist-info/LICENSE
clesperanto-0.1.3.dist-info/METADATA
clesperanto-0.1.3.dist-info/WHEEL
clesperanto-0.1.3.dist-info/entry_points.txt
clesperanto-0.1.3.dist-info/top_level.txt
clesperanto-0.1.3.dist-info/RECORD
