Metadata-Version: 2.1
Name: clesperanto
Version: 0.1.3
Summary: A graphical user interface for clesperanto based on napari
Home-page: https://github.com/clEsperanto/pyclesperanto_prototype
Author: Robert Haase
Author-email: robert.haase@tu-dresden.de
License: UNKNOWN
Platform: UNKNOWN
Classifier: Programming Language :: Python :: 3
Classifier: License :: OSI Approved :: BSD License
Classifier: Operating System :: OS Independent
Classifier: Intended Audience :: Science/Research
Classifier: Development Status :: 3 - Alpha
Requires-Python: >=3.6
License-File: LICENSE
Requires-Dist: numpy (!=1.19.4)
Requires-Dist: pyopencl
Requires-Dist: toolz
Requires-Dist: scikit-image (>=0.18.0)
Requires-Dist: matplotlib
Requires-Dist: transforms3d
Requires-Dist: napari[all]
Requires-Dist: napari-pyclesperanto-assistant
Requires-Dist: napari-accelerated-pixel-and-object-classification
Requires-Dist: napari-brightness-contrast
Requires-Dist: napari-mouse-controls
Requires-Dist: napari-plot-profile
Requires-Dist: napari-skimage-regionprops
Requires-Dist: napari-segment-blobs-and-things-with-membranes
Requires-Dist: napari-tabu
Requires-Dist: napari-crop
Requires-Dist: napari-layer-details-display
